Workbook

Sheet Dashboard
B2: Суть проекта:
B4: Рассматриваются 2 возможные опции замены/импортозамещения Gitlab Premium:
B5: Покупка лицензии GitFlic или собственная разработка в рамках VK Tech Dev Platform
B6: В рамках покупки лицензии GitFlic доступно 2 опции: базовая поддержка L3 (Сценарий 1) или привилегированная поддержка L3 (Сценарий 1.1).
B8: Оба варианта находятся в доработке.
B9: GitFlick закроет потребности ВК в Q4 2024 при выполнении заявленных планов доработки.
B10: VK Tech необходимо инвестировать в ФОТ, чтобы покрыть потребности ВК к Q4 2024.
B11: По информации от VK Tech, после завершения разработки в 2024, команда переводится на другие проекты, для оперирования необходима только техническая поддержка.
B13: Совокупные затраты, тыс. руб.: | C13: 1 год эксплуатации | D13: 3 года эксплуатации
B14: Покупка лицензии GitFlic (базовая поддержка L3) | C14: =SUM(Calc!D13:I13) -> 332857.13 | D14: =SUM(Calc!D13:K13) -> 765642.13
B15: Покупка лицензии GitFlic (привилегированная поддержка L3) | C15: =SUM(Calc!D58:I58) -> 644144.47 | D15: =SUM(Calc!D58:K58) -> 1556961
B16: Собственная разработка VK Tech Dev Platform | C16: =SUM(Calc!D102:I102) -> 202433.44 | D16: =SUM(Calc!D102:K102) -> 291268.35
B18: Сценарий:
B19: =CHOOSE(Calc!$M$124,"базовая поддержка GitFlic","привелиг. поддержка GitFlic") -> базовая поддержка GitFlic
B20: NPV @20% | C20: х | D20: =Calc!D134 -> 280249.68
B21: IRR | C21: % | D21: =Calc!D135 -> 2.6743605
B22: Срок окупаемости | C22: лет | D22: =Calc!D136 -> 1.2454629
B23: Дисконт. срок окупаемости | C23: лет | D23: =Calc!D137 -> 1.3107387
C28: 2023 | D28: 2024 | E28: 2025 | F28: 2026 | G28: 2027 | H28: Итого
B29: Покупка лицензии GitFlic (базовая поддержка L3) | C29: =Calc!D13 -> 0 | D29: =SUM(Calc!E13:H13) -> 108067.87 | E29: =Calc!I13 -> 224789.26 | F29: =Calc!J13 -> 215708.8 | G29: =Calc!K13 -> 217076.19 | H29: =SUM(C29:G29) -> 765642.13
B30: Покупка лицензии GitFlic (привилегированная поддержка L3) | C30: =Calc!D58 -> 0 | D30: =SUM(Calc!E58:H58) -> 178397.78 | E30: =Calc!I58 -> 465746.69 | F30: =Calc!J58 -> 455793.17 | G30: =Calc!K58 -> 457023.37 | H30: =SUM(C30:G30) -> 1556961
B31: Собственная разработка VK Tech Dev Platform | C31: =Calc!D102 -> 7000 | D31: =SUM(Calc!E102:H102) -> 143496.77 | E31: =Calc!I102 -> 51936.67 | F31: =Calc!J102 -> 42302.337 | G31: =Calc!K102 -> 46532.571 | H31: =SUM(C31:G31) -> 291268.35
B35: Разбивка расходов (суммарно 2023-2027 гг.) по категориям | C35: Gitflic баз. | D35: Gitflic - прив. | E35: DevPlatform
B36: Лицензии | C36: =SUM(Calc!D7:K7) -> 584193.6 | D36: =SUM(Calc!D52:K52) -> 584193.6 | E36: 0
B37: Разработка | C37: 0 | D37: 0 | E37: =SUM(Calc!D96:K96) -> 86500
B38: Внедрение (команда VK) | C38: =SUM(Calc!D8:K8) -> 38250 | D38: =SUM(Calc!D53:K53) -> 38250 | E38: =SUM(Calc!D97:K97) -> 34500
B39: Поддержка L1-2 | C39: =SUM(Calc!D10:K10) -> 33415.2 | D39: =SUM(Calc!D55:K55) -> 33415.2 | E39: =SUM(Calc!D99:K99) -> 33415.2
B40: Поддержка L3 | C40: =SUM(Calc!D11:K11) -> 81138 | D40: =SUM(Calc!D56:K56) -> 876290.4 | E40: =SUM(Calc!D100:K100) -> 106384
B41: Прочее | C41: =SUM(Calc!D9:K9,Calc!D12:K12) -> 28645.327 | D41: =SUM(Calc!D54:K54,Calc!D57:K57) -> 24811.811 | E41: =SUM(Calc!D101:K101,Calc!D98:K98) -> 30469.147
B42: Итого: | C42: =SUM(C36:C41) -> 765642.13 | D42: =SUM(D36:D41) -> 1556961 | E42: =SUM(E36:E41) -> 291268.35
C43: =C42-H29 -> 0 | D43: =D42-H30 -> 0 | E43: =E42-H31 -> 0

Sheet Calc
B2: Расчет расходов
B4: Сценарий 1. Покупка лицензии GitFlic
B6: Показатель | C6: ед. изм. | D6: 2023 | E6: 1Q 2024 | F6: 2Q 2024 | G6: 3Q 2024 | H6: 4Q 2024 | I6: 2025 | J6: 2026 | K6: 2027 | O6: Источники информации:
B7: Покупка лицензий | C7: тыс. руб. | D7: =D16*D17*D19*(1-D20) -> 0 | E7: =E16*E17*E19*(1-E20) -> 1460.16 | F7: =F16*F17*F19*(1-F20) -> 12839.04 | G7: =G16*G17*G19*(1-G20) -> 12839.04 | H7: =H16*H17*H19*(1-H20) -> 24865.92 | I7: =I16*I17*I19*(1-I20) -> 177396.48 | J7: =J16*J17*J19*(1-J20) -> 177396.48 | K7: =K16*K17*K19*(1-K20) -> 177396.48
B8: Затраты на внедрение (команда со стороны VK) | C8: тыс. руб. | D8: =D23*D24*D25 -> 0 | E8: =E23*E24*E25 -> 7500 | F8: =F23*F24*F25 -> 7500 | G8: =G23*G24*G25 -> 7500 | H8: =H23*H24*H25 -> 7500 | I8: =I23*I24*I25 -> 8250 | J8: =J23*J24*J25 -> 0 | K8: =K23*K24*K25 -> 0
B9: ФОТ сис. админов (эксплуатация) | C9: тыс. руб. | D9: =D30*D28*D29 -> 0 | E9: =E30*E28*E29 -> 2400 | F9: =F30*F28*F29 -> 2400 | G9: =G30*G28*G29 -> 2400 | H9: =H30*H28*H29 -> 2400 | I9: =I30*I28*I29 -> 4620 | J9: =J30*J28*J29 -> 2904 | K9: =K30*K28*K29 -> 3194.4
B10: Затраты на тех. поддержку L1-L2 | C10: тыс. руб. | D10: =D35*D33*D34 -> 0 | E10: =E35*E33*E34 -> 1800 | F10: =F35*F33*F34 -> 1800 | G10: =G35*G33*G34 -> 1800 | H10: =H35*H33*H34 -> 1800 | I10: =I35*I33*I34 -> 7920 | J10: =J35*J33*J34 -> 8712 | K10: =K35*K33*K34 -> 9583.2
B11: Базовая техподдержка L3 (Gitflic) | C11: тыс. руб. | D11: =D38*D39*D40*(1-D41) -> 0 | E11: =E38*E39*E40*(1-E41) -> 202.8 | F11: =F38*F39*F40*(1-F41) -> 1783.2 | G11: =G38*G39*G40*(1-G41) -> 1783.2 | H11: =H38*H39*H40*(1-H41) -> 3453.6 | I11: =I38*I39*I40*(1-I41) -> 24638.4 | J11: =J38*J39*J40*(1-J41) -> 24638.4 | K11: =K38*K39*K40*(1-K41) -> 24638.4
B12: Накладные расходы | C12: тыс. руб. | D12: =D44*D45*D46 -> 0 | E12: =E44*E45*E46 -> 510.22835 | F12: =F44*F45*F46 -> 510.22835 | G12: =G44*G45*G46 -> 510.22835 | H12: =H44*H45*H46 -> 510.22835 | I12: =I44*I45*I46 -> 1964.3792 | J12: =J44*J45*J46 -> 2057.921 | K12: =K44*K45*K46 -> 2263.7131
B13: Итого расходы | C13: тыс. руб. | D13: =SUM(D7:D12) -> 0 | E13: =SUM(E7:E12) -> 13873.188 | F13: =SUM(F7:F12) -> 26832.468 | G13: =SUM(G7:G12) -> 26832.468 | H13: =SUM(H7:H12) -> 40529.748 | I13: =SUM(I7:I12) -> 224789.26 | J13: =SUM(J7:J12) -> 215708.8 | K13: =SUM(K7:K12) -> 217076.19 | L13: =SUM(D13:K13) -> 765642.13
B15: Расчет стоимости лицензий
B16: Стоимость 1 лицензии на 1 чел. в месяц (с базовой поддержкой) | C16: тыс. руб./чел./мес. | D16: =Inputs!C4 -> 3.6 | E16: =D16 -> 3.6 | F16: =E16 -> 3.6 | G16: =F16 -> 3.6 | H16: =G16 -> 3.6 | I16: =H16 -> 3.6 | J16: =I16 -> 3.6 | K16: =J16 -> 3.6 | O16: Лицензия с обновлениями и базовой поддержкой - 3600 р Лицензия с обновлениями и привилегированной поддержкой - 9000 р.
B17: Кол-во месяцев | C17: мес. | D17: 0 | E17: 3 | F17: 3 | G17: 3 | H17: 3 | I17: 12 | J17: 12 | K17: 12
B18: Кол-во лицензий, купленных в текущем периоде | C18: ед. | D18: 0 | E18: ='Лицензии GitFlic'!B12 -> 169 | F18: ='Лицензии GitFlic'!C12 -> 1317 | G18: ='Лицензии GitFlic'!D12 -> 0 | H18: ='Лицензии GitFlic'!E12 -> 1392 | I18: ='Лицензии GitFlic'!F12+'Лицензии GitFlic'!G12 -> 2255 | J18: 0 | K18: 0
B19: Кол-во лицензий на конец года накоп. итогом | C19: ед. | D19: =D18 -> 0 | E19: =D19+E18 -> 169 | F19: =E19+F18 -> 1486 | G19: =F19+G18 -> 1486 | H19: =G19+H18 -> 2878 | I19: =H19+I18 -> 5133 | J19: =I19+J18 -> 5133 | K19: =J19+K18 -> 5133 | O19: https://docs.google.com/spreadsheets/d/1scDRa_J-A9aYaQ8FAMvMXZFliANVjIY1AZQ8vsE5h1Y/edit#gid=0
B20: Скидка | C20: % | D20: 0.2 | E20: =D20 -> 0.2 | F20: =E20 -> 0.2 | G20: =F20 -> 0.2 | H20: =G20 -> 0.2 | I20: =H20 -> 0.2 | J20: =I20 -> 0.2 | K20: =J20 -> 0.2 | O20: комментарий команды ВК: в случае приобретения лицензии GitFlic, можем рассчитывать на скидку 20% на весь срок использования
B22: Затраты на внедрение (команда со стороны VK)
B23: FTE | C23: ставок | D23: 5 | E23: =D23 -> 5 | F23: =E23 -> 5 | G23: =F23 -> 5 | H23: =G23 -> 5 | I23: =H23 -> 5 | J23: =I23 -> 5 | K23: =J23 -> 5 | O23: добавляем одного человека к команде внедрения GitFlic на стороне VK. 5 вместо 4х для DevPlatform оставляем 4
B24: Заработная плата в месяц | C24: тыс. руб./месяц | D24: =Dev_Platform_Hosted_Git!B26 -> 500 | E24: =D24 -> 500 | F24: =E24 -> 500 | G24: =F24 -> 500 | H24: =G24 -> 500 | I24: =E24*1.1 -> 550 | J24: =I24*1.1 -> 605 | K24: =J24*1.1 -> 665.5
B25: Кол-во месяцев | C25: мес. | D25: 0 | E25: =E17 -> 3 | F25: =F17 -> 3 | G25: =G17 -> 3 | H25: =H17 -> 3 | I25: 3 | J25: 0 | K25: 0 | O25: 3 постоянных FTE на весь срок внедрения. последнюю партию начинаем внедрять в Q1 2025.
B27: Расчет ФОТ сис. админов
B28: FTE | C28: ставок | D28: 0 | E28: 2 | F28: =E28 -> 2 | G28: =F28 -> 2 | H28: =G28 -> 2 | I28: =2*I25/I17+0.5*(1-I25/I17) -> 0.875 | J28: 0.5 | K28: =J28 -> 0.5 | O28: в 2024 (год внедрения) эксплуатация 2 FTE (400 тыс. на 1 FTE) ежемесячно для обоих решений. В 2025 внедрение идет только в 1Q (2FTE). Далее - 0.5 FTE.
B29: Заработная плата в месяц | C29: тыс. руб./месяц | D29: 400 | E29: =D29 -> 400 | F29: =E29 -> 400 | G29: =F29 -> 400 | H29: =G29 -> 400 | I29: =E29*1.1 -> 440 | J29: =I29*1.1 -> 484 | K29: =J29*1.1 -> 532.4
B30: Кол-во месяцев | C30: мес. | D30: =D17 -> 0 | E30: =E17 -> 3 | F30: =F17 -> 3 | G30: =G17 -> 3 | H30: =H17 -> 3 | I30: =I17 -> 12 | J30: =J17 -> 12 | K30: =K17 -> 12 | O30: поддержка L1-L3 начиная с начала внедрения
B32: Затраты на тех. поддержку L1-L2
B33: З/п 1 сотрудника в месяц | C33: тыс. руб./месяц | D33: 300 | E33: =D33 -> 300 | F33: =E33 -> 300 | G33: =F33 -> 300 | H33: =G33 -> 300 | I33: =E33*1.1 -> 330 | J33: =I33*1.1 -> 363 | K33: =J33*1.1 -> 399.3
B34: Кол-во месяцев | C34: мес. | D34: 0 | E34: 3 | F34: 3 | G34: 3 | H34: 3 | I34: 12 | J34: 12 | K34: 12 | O34: техподдержка уровней L1 и L2 - 2 FTE начиная с 1 месяца внедрения
B35: FTE | C35: чел. | D35: 2 | E35: =D35 -> 2 | F35: =E35 -> 2 | G35: =F35 -> 2 | H35: =G35 -> 2 | I35: =H35 -> 2 | J35: =I35 -> 2 | K35: =J35 -> 2
B37: Базовая тех. поддержка L3 (Gitflic)
B38: Стоимость поддержки на 1 лицензию в месяц | C38: тыс. руб./месяц/1 лиц. | D38: 0.5 | E38: =D38 -> 0.5 | F38: =E38 -> 0.5 | G38: =F38 -> 0.5 | H38: =G38 -> 0.5 | I38: =H38 -> 0.5 | J38: =I38 -> 0.5 | K38: =J38 -> 0.5 | O38: базовая техподдержка L3 gitflic - 500 рублей в месяц за одну лицензию
B39: Кол-во лицензий на конец года | C39: ед. | D39: =D19 -> 0 | E39: =E19 -> 169 | F39: =F19 -> 1486 | G39: =G19 -> 1486 | H39: =H19 -> 2878 | I39: =I19 -> 5133 | J39: =J19 -> 5133 | K39: =K19 -> 5133
B40: Кол-во месяцев | C40: мес. | D40: =D17 -> 0 | E40: =E17 -> 3 | F40: =F17 -> 3 | G40: =G17 -> 3 | H40: =H17 -> 3 | I40: =I17 -> 12 | J40: =J17 -> 12 | K40: =K17 -> 12
B41: Скидка | C41: % | D41: 0.2 | E41: =D41 -> 0.2 | F41: =E41 -> 0.2 | G41: =F41 -> 0.2 | H41: =G41 -> 0.2 | I41: =H41 -> 0.2 | J41: =I41 -> 0.2 | K41: =J41 -> 0.2
B43: Накладные расходы
B44: Накладные расходы на 1 сотр. | C44: тыс. руб./мес./чел. | D44: =D105 -> 17.179406 | E44: =D44*1.1 -> 18.897346 | F44: =E44 -> 18.897346 | G44: =F44 -> 18.897346 | H44: =G44 -> 18.897346 | I44: =H44*1.1 -> 20.787081 | J44: =I44*1.1 -> 22.865789 | K44: =J44*1.1 -> 25.152368 | O44: данные по величине накладных расходов в расчете на 1 сотрудника по MRCS VK Cloud Solutions (куда входит МВЗ Dev Platform), бюджет на 2024 г., данные SAP
B45: FTE разработки, внедрения, тех. поддержки | C45: ставок | D45: =D23+D28+D35 -> 7 | E45: =E23+E28+E35 -> 9 | F45: =F23+F28+F35 -> 9 | G45: =G23+G28+G35 -> 9 | H45: =H23+H28+H35 -> 9 | I45: =I23+I28+I35 -> 7.875 | J45: =J23+J28+J35 -> 7.5 | K45: =K23+K28+K35 -> 7.5 | O45: https://docs.google.com/spreadsheets/d/18zoRAiluOu8OSHcklXl1pKDKYutyzjw8/edit#gid=1032846955
B46: Кол-во месяцев | C46: мес. | D46: 0 | E46: =E17 -> 3 | F46: =F17 -> 3 | G46: =G17 -> 3 | H46: =H17 -> 3 | I46: =I17 -> 12 | J46: =J17 -> 12 | K46: =K17 -> 12
B49: Сценарий 1.1. Покупка лицензии GitFlic с привилегированной поддержкой
B51: Показатель | C51: ед. изм. | D51: 2023 | E51: 1Q 2024 | F51: 2Q 2024 | G51: 3Q 2024 | H51: 4Q 2024 | I51: 2025 | J51: 2026 | K51: 2027
B52: Покупка лицензий | C52: тыс. руб. | D52: =D61*D62*D64*(1-D65) -> 0 | E52: =E61*E62*E64*(1-E65) -> 1460.16 | F52: =F61*F62*F64*(1-F65) -> 12839.04 | G52: =G61*G62*G64*(1-G65) -> 12839.04 | H52: =H61*H62*H64*(1-H65) -> 24865.92 | I52: =I61*I62*I64*(1-I65) -> 177396.48 | J52: =J61*J62*J64*(1-J65) -> 177396.48 | K52: =K61*K62*K64*(1-K65) -> 177396.48
B53: Затраты на внедрение (команда со стороны VK) | C53: тыс. руб. | D53: =D68*D69*D70 -> 0 | E53: =E68*E69*E70 -> 7500 | F53: =F68*F69*F70 -> 7500 | G53: =G68*G69*G70 -> 7500 | H53: =H68*H69*H70 -> 7500 | I53: =I68*I69*I70 -> 8250 | J53: =J68*J69*J70 -> 0 | K53: =K68*K69*K70 -> 0
B54: ФОТ сис. админов (эксплуатация) | C54: тыс. руб. | D54: =D75*D73*D74 -> 0 | E54: =E75*E73*E74 -> 2400 | F54: =F75*F73*F74 -> 2400 | G54: =G75*G73*G74 -> 2400 | H54: =H75*H73*H74 -> 2400 | I54: =I75*I73*I74 -> 4620 | J54: =J75*J73*J74 -> 2904 | K54: =K75*K73*K74 -> 3194.4
B55: Затраты на тех. поддержку L1-L2 | C55: тыс. руб. | D55: =D80*D78*D79 -> 0 | E55: =E80*E78*E79 -> 1800 | F55: =F80*F78*F79 -> 1800 | G55: =G80*G78*G79 -> 1800 | H55: =H80*H78*H79 -> 1800 | I55: =I80*I78*I79 -> 7920 | J55: =J80*J78*J79 -> 8712 | K55: =K80*K78*K79 -> 9583.2
B56: Привилегированная техподдержка L3 (Gitflic) | C56: тыс. руб. | D56: =D83*D84*D85*(1-D86) -> 0 | E56: =E83*E84*E85*(1-E86) -> 2190.24 | F56: =F83*F84*F85*(1-F86) -> 19258.56 | G56: =G83*G84*G85*(1-G86) -> 19258.56 | H56: =H83*H84*H85*(1-H86) -> 37298.88 | I56: =I83*I84*I85*(1-I86) -> 266094.72 | J56: =J83*J84*J85*(1-J86) -> 266094.72 | K56: =K83*K84*K85*(1-K86) -> 266094.72 | O56: стоимость внедрения и миграции GitFlic - включена в стоимость привилегированной техподдержки
B57: Накладные расходы | C57: тыс. руб. | D57: =D89*D90*D91 -> 0 | E57: =E89*E90*E91 -> 396.84428 | F57: =F89*F90*F91 -> 396.84428 | G57: =G89*G90*G91 -> 396.84428 | H57: =H89*H90*H91 -> 396.84428 | I57: =I89*I90*I91 -> 1465.4892 | J57: =J89*J90*J91 -> 685.97368 | K57: =K89*K90*K91 -> 754.57104
B58: Итого расходы | C58: тыс. руб. | D58: =SUM(D52:D57) -> 0 | E58: =SUM(E52:E57) -> 15747.244 | F58: =SUM(F52:F57) -> 44194.444 | G58: =SUM(G52:G57) -> 44194.444 | H58: =SUM(H52:H57) -> 74261.644 | I58: =SUM(I52:I57) -> 465746.69 | J58: =SUM(J52:J57) -> 455793.17 | K58: =SUM(K52:K57) -> 457023.37 | L58: =SUM(D58:K58) -> 1556961
B60: Расчет стоимости лицензий
B61: Стоимость 1 лицензии на 1 чел. в месяц (с базовой поддержкой) | C61: тыс. руб./чел./мес. | D61: =D16 -> 3.6 | E61: =D61 -> 3.6 | F61: =E61 -> 3.6 | G61: =F61 -> 3.6 | H61: =G61 -> 3.6 | I61: =H61 -> 3.6 | J61: =I61 -> 3.6 | K61: =J61 -> 3.6 | O61: https://docs.google.com/spreadsheets/d/1scDRa_J-A9aYaQ8FAMvMXZFliANVjIY1AZQ8vsE5h1Y/edit#gid=0
B62: Кол-во месяцев | C62: мес. | D62: =D17 -> 0 | E62: =E17 -> 3 | F62: =F17 -> 3 | G62: =G17 -> 3 | H62: =H17 -> 3 | I62: =I17 -> 12 | J62: =J17 -> 12 | K62: =K17 -> 12
B63: Кол-во лицензий, купленных в текущем периоде | C63: ед. | D63: =D18 -> 0 | E63: =E18 -> 169 | F63: =F18 -> 1317 | G63: =G18 -> 0 | H63: =H18 -> 1392 | I63: =I18 -> 2255 | J63: =J18 -> 0 | K63: =K18 -> 0
B64: Кол-во лицензий на конец года | C64: ед. | D64: =D63 -> 0 | E64: =D64+E63 -> 169 | F64: =E64+F63 -> 1486 | G64: =F64+G63 -> 1486 | H64: =G64+H63 -> 2878 | I64: =H64+I63 -> 5133 | J64: =I64+J63 -> 5133 | K64: =J64+K63 -> 5133 | O64: https://docs.google.com/spreadsheets/d/1scDRa_J-A9aYaQ8FAMvMXZFliANVjIY1AZQ8vsE5h1Y/edit#gid=0
B65: Скидка | C65: % | D65: 0.2 | E65: =D65 -> 0.2 | F65: =E65 -> 0.2 | G65: =F65 -> 0.2 | H65: =G65 -> 0.2 | I65: =H65 -> 0.2 | J65: =I65 -> 0.2 | K65: =J65 -> 0.2 | O65: комментарий команды ВК: в случае приобретения лицензии GitFlic, можем рассчитывать на скидку 20% на весь срок использования
B67: Затраты на внедрение (команда со стороны VK)
B68: FTE | C68: ставок | D68: =D23 -> 5 | E68: =D68 -> 5 | F68: =E68 -> 5 | G68: =F68 -> 5 | H68: =G68 -> 5 | I68: =H68 -> 5 | J68: =I68 -> 5 | K68: =J68 -> 5 | O68: добавляем одного человека к команде внедрения GitFlic на стороне VK. 5 вместо 4х для DevPlatform оставляем 4
B69: Заработная плата в месяц | C69: тыс. руб./месяц | D69: =Dev_Platform_Hosted_Git!B26 -> 500 | E69: =D69 -> 500 | F69: =E69 -> 500 | G69: =F69 -> 500 | H69: =G69 -> 500 | I69: =E69*1.1 -> 550 | J69: =I69*1.1 -> 605 | K69: =J69*1.1 -> 665.5
B70: Кол-во месяцев | C70: мес. | D70: =D25 -> 0 | E70: =E25 -> 3 | F70: =F25 -> 3 | G70: =G25 -> 3 | H70: =H25 -> 3 | I70: =I25 -> 3 | J70: =J25 -> 0 | K70: =K25 -> 0 | O70: 3 постоянных FTE на весь срок внедрения (1,5 года)
B72: Расчет ФОТ сис. админов
B73: FTE | C73: ставок | D73: =D28 -> 0 | E73: =E28 -> 2 | F73: =F28 -> 2 | G73: =G28 -> 2 | H73: =H28 -> 2 | I73: =I28 -> 0.875 | J73: =J28 -> 0.5 | K73: =K28 -> 0.5 | O73: в 2024 (год внедрения) эксплуатация 2 FTE (400 тыс. на 1 FTE) ежемесячно для обоих решений. В 2025 внедрение идет только в 1Q (2FTE). Далее - 0.5 FTE.
B74: Заработная плата в месяц | C74: тыс. руб./месяц | D74: 400 | E74: =D74 -> 400 | F74: =E74 -> 400 | G74: =F74 -> 400 | H74: =G74 -> 400 | I74: =E74*1.1 -> 440 | J74: =I74*1.1 -> 484 | K74: =J74*1.1 -> 532.4
B75: Кол-во месяцев | C75: мес. | D75: =D30 -> 0 | E75: =E30 -> 3 | F75: =F30 -> 3 | G75: =G30 -> 3 | H75: =H30 -> 3 | I75: =I30 -> 12 | J75: =J30 -> 12 | K75: =K30 -> 12
B77: Затраты на тех. поддержку L1-L2
B78: З/п 1 сотрудника в месяц | C78: тыс. руб./месяц | D78: 300 | E78: =D78 -> 300 | F78: =E78 -> 300 | G78: =F78 -> 300 | H78: =G78 -> 300 | I78: =E78*1.1 -> 330 | J78: =I78*1.1 -> 363 | K78: =J78*1.1 -> 399.3
B79: Кол-во месяцев | C79: мес. | D79: =D34 -> 0 | E79: =E34 -> 3 | F79: =F34 -> 3 | G79: =G34 -> 3 | H79: =H34 -> 3 | I79: =I34 -> 12 | J79: =J34 -> 12 | K79: =K34 -> 12
B80: FTE | C80: чел. | D80: 2 | E80: =D80 -> 2 | F80: =E80 -> 2 | G80: =F80 -> 2 | H80: =G80 -> 2 | I80: =H80 -> 2 | J80: =I80 -> 2 | K80: =J80 -> 2 | O80: техподдержка уровней L1 и L2 - 2 FTE начиная с 1 месяца внедрения
B82: Привилегированная тех. поддержка L3 (Gitflic)
B83: Стоимость поддержки на 1 лицензию в месяц | C83: тыс. руб./месяц/1 лиц. | D83: =9-D16 -> 5.4 | E83: =D83 -> 5.4 | F83: =E83 -> 5.4 | G83: =F83 -> 5.4 | H83: =G83 -> 5.4 | I83: =H83 -> 5.4 | J83: =I83 -> 5.4 | K83: =J83 -> 5.4 | O83: привилегированная техподдержка L3 gitflic - (9000-3600) рублей в месяц за одну лицензию + скидка 20%
B84: Кол-во лицензий на конец года | C84: ед. | D84: =D64 -> 0 | E84: =E64 -> 169 | F84: =F64 -> 1486 | G84: =G64 -> 1486 | H84: =H64 -> 2878 | I84: =I64 -> 5133 | J84: =J64 -> 5133 | K84: =K64 -> 5133
B85: Кол-во месяцев | C85: мес. | D85: =D62 -> 0 | E85: =E62 -> 3 | F85: =F62 -> 3 | G85: =G62 -> 3 | H85: =H62 -> 3 | I85: =I62 -> 12 | J85: =J62 -> 12 | K85: =K62 -> 12
B86: Скидка | C86: % | D86: 0.2 | E86: =D86 -> 0.2 | F86: =E86 -> 0.2 | G86: =F86 -> 0.2 | H86: =G86 -> 0.2 | I86: =H86 -> 0.2 | J86: =I86 -> 0.2 | K86: =J86 -> 0.2
B88: Накладные расходы
B89: Накладные расходы на 1 сотр. | C89: тыс. руб./мес./чел. | D89: =D105 -> 17.179406 | E89: =D89*1.1 -> 18.897346 | F89: =E89 -> 18.897346 | G89: =F89 -> 18.897346 | H89: =G89 -> 18.897346 | I89: =H89*1.1 -> 20.787081 | J89: =I89*1.1 -> 22.865789 | K89: =J89*1.1 -> 25.152368 | O89: данные по величине накладных расходов в расчете на 1 сотрудника по MRCS VK Cloud Solutions (куда входит МВЗ Dev Platform), бюджет на 2024 г., данные SAP
B90: FTE разработки, внедрения, тех. поддержки | C90: ставок | D90: =D70+D73+D80 -> 2 | E90: =E70+E73+E80 -> 7 | F90: =F70+F73+F80 -> 7 | G90: =G70+G73+G80 -> 7 | H90: =H70+H73+H80 -> 7 | I90: =I70+I73+I80 -> 5.875 | J90: =J70+J73+J80 -> 2.5 | K90: =K70+K73+K80 -> 2.5 | O90: https://docs.google.com/spreadsheets/d/18zoRAiluOu8OSHcklXl1pKDKYutyzjw8/edit#gid=1032846955
B91: Кол-во месяцев | C91: мес. | D91: 0 | E91: =E62 -> 3 | F91: =F62 -> 3 | G91: =G62 -> 3 | H91: =H62 -> 3 | I91: =I62 -> 12 | J91: =J62 -> 12 | K91: =K62 -> 12
B93: Сценарий 2. Разработка собственного решения Dev Platform
E94: 2024 | F94: 2024 | G94: 2024 | H94: 2024
B95: Показатель | C95: ед. изм. | D95: 2023 | E95: 1Q 2024 | F95: 2Q 2024 | G95: 3Q 2024 | H95: 4Q 2024 | I95: 2025 | J95: 2026 | K95: 2027
B96: Инвестиции на разработку | C96: тыс. руб. | D96: =SUMIF(Dev_Platform_Hosted_Git!$4:$4,Calc!D$95,Dev_Platform_Hosted_Git!$19:$19) -> 7000 | E96: =SUMIF(Dev_Platform_Hosted_Git!$4:$4,Calc!E$94,Dev_Platform_Hosted_Git!$19:$19)/4 -> 19875 | F96: =SUMIF(Dev_Platform_Hosted_Git!$4:$4,Calc!F$94,Dev_Platform_Hosted_Git!$19:$19)/4 -> 19875 | G96: =SUMIF(Dev_Platform_Hosted_Git!$4:$4,Calc!G$94,Dev_Platform_Hosted_Git!$19:$19)/4 -> 19875 | H96: =SUMIF(Dev_Platform_Hosted_Git!$4:$4,Calc!H$94,Dev_Platform_Hosted_Git!$19:$19)/4 -> 19875 | I96: 0 | J96: 0 | K96: 0 | O96: https://docs.google.com/spreadsheets/d/18zoRAiluOu8OSHcklXl1pKDKYutyzjw8/edit#gid=1032846955
B97: Затраты на внедрение | C97: тыс. руб. | D97: =SUMIF(Dev_Platform_Hosted_Git!$4:$4,Calc!D$95,Dev_Platform_Hosted_Git!$27:$27) -> 0 | E97: =SUMIF(Dev_Platform_Hosted_Git!$4:$4,Calc!E$94,Dev_Platform_Hosted_Git!$27:$27)/4 -> 5750 | F97: =SUMIF(Dev_Platform_Hosted_Git!$4:$4,Calc!F$94,Dev_Platform_Hosted_Git!$27:$27)/4 -> 5750 | G97: =SUMIF(Dev_Platform_Hosted_Git!$4:$4,Calc!G$94,Dev_Platform_Hosted_Git!$27:$27)/4 -> 5750 | H97: =SUMIF(Dev_Platform_Hosted_Git!$4:$4,Calc!H$94,Dev_Platform_Hosted_Git!$27:$27)/4 -> 5750 | I97: =Dev_Platform_Hosted_Git!C28 -> 11500 | J97: 0 | K97: 0 | O97: https://docs.google.com/spreadsheets/d/18zoRAiluOu8OSHcklXl1pKDKYutyzjw8/edit#gid=1032846955
B98: Накладные расходы | C98: тыс. руб. | D98: =D105*D106*D107 -> 0 | E98: =E105*E106*E107 -> 1299.1926 | F98: =F105*F106*F107 -> 1299.1926 | G98: =G105*G106*G107 -> 1299.1926 | H98: =H105*H106*H107 -> 1299.1926 | I98: =I105*I106*I107 -> 1496.6698 | J98: =J105*J106*J107 -> 1646.3368 | K98: =K105*K106*K107 -> 1810.9705
B99: Затраты на тех. поддержку L1-L2 | C99: тыс. руб. | D99: =D112*D110*D111 -> 0 | E99: =E112*E110*E111 -> 1800 | F99: =F112*F110*F111 -> 1800 | G99: =G112*G110*G111 -> 1800 | H99: =H112*H110*H111 -> 1800 | I99: =I112*I110*I111 -> 7920 | J99: =J112*J110*J111 -> 8712 | K99: =K112*K110*K111 -> 9583.2
B100: Затраты на тех. поддержку L3 (VK Tech) | C100: тыс. руб. | D100: =D117*D115*D116 -> 0 | E100: =E117*E115*E116 -> 1000 | F100: =F117*F115*F116 -> 6000 | G100: =G117*G115*G116 -> 6000 | H100: =H117*H115*H116 -> 6000 | I100: =I117*I115*I116 -> 26400 | J100: =J117*J115*J116 -> 29040 | K100: =K117*K115*K116 -> 31944
B101: ФОТ сис. админов (эксплуатация) | C101: тыс. руб. | D101: =D30*D28*D29 -> 0 | E101: =E30*E28*E29 -> 2400 | F101: =F30*F28*F29 -> 2400 | G101: =G30*G28*G29 -> 2400 | H101: =H30*H28*H29 -> 2400 | I101: =I30*I28*I29 -> 4620 | J101: =J30*J28*J29 -> 2904 | K101: =K30*K28*K29 -> 3194.4
B102: Итого расходы | C102: тыс. руб. | D102: =SUM(D96:D101) -> 7000 | E102: =SUM(E96:E101) -> 32124.193 | F102: =SUM(F96:F101) -> 37124.193 | G102: =SUM(G96:G101) -> 37124.193 | H102: =SUM(H96:H101) -> 37124.193 | I102: =SUM(I96:I101) -> 51936.67 | J102: =SUM(J96:J101) -> 42302.337 | K102: =SUM(K96:K101) -> 46532.571 | L102: =SUM(D102:K102) -> 291268.35
B104: Накладные расходы
B105: Накладные расходы на 1 сотр. | C105: тыс. руб./мес./чел. | D105: =-SAP!G59/12/10^3 -> 17.179406 | E105: =D105*1.1 -> 18.897346 | F105: =E105 -> 18.897346 | G105: =F105 -> 18.897346 | H105: =G105 -> 18.897346 | I105: =H105*1.1 -> 20.787081 | J105: =I105*1.1 -> 22.865789 | K105: =J105*1.1 -> 25.152368 | O105: данные по величине накладных расходов в расчете на 1 сотрудника по MRCS VK Cloud Solutions (куда входит МВЗ Dev Platform), бюджет на 2024 г., данные SAP
B106: FTE разработки, внедрения, тех. поддержки | C106: ставок | D106: =SUMPRODUCT(Dev_Platform_Hosted_Git!D15:E15,Dev_Platform_Hosted_Git!D16:E16)/SUM(Dev_Platform_Hosted_Git!D16:E16)+D112+D117 -> 9 | E106: =SUMPRODUCT(Dev_Platform_Hosted_Git!F15:Q15,Dev_Platform_Hosted_Git!F16:Q16)/SUM(Dev_Platform_Hosted_Git!F16:Q16)+SUMPRODUCT(Dev_Platform_Hosted_Git!F25:Q25,Dev_Platform_Hosted_Git!F29:Q29)/SUM(Dev_Platform_Hosted_Git!F29:Q29)+SUMPRODUCT(Dev_Platform_Hosted_Git!F36:Q36,Dev_Platform_Hosted_Git!F40:Q40)/SUM(Dev_Platform_Hosted_Git!F40:Q40)+E112+E117 -> 22.916667 | F106: =E106 -> 22.916667 | G106: =F106 -> 22.916667 | H106: =G106 -> 22.916667 | I106: =I112+I117 -> 6 | J106: =J112+J117 -> 6 | K106: =K112+K117 -> 6 | O106: https://docs.google.com/spreadsheets/d/18zoRAiluOu8OSHcklXl1pKDKYutyzjw8/edit#gid=1032846955
B107: Кол-во месяцев | C107: мес. | D107: =D17 -> 0 | E107: =E17 -> 3 | F107: =F17 -> 3 | G107: =G17 -> 3 | H107: =H17 -> 3 | I107: =I17 -> 12 | J107: =J17 -> 12 | K107: =K17 -> 12
B109: Затраты на тех. поддержку L1-L2
B110: З/п 1 сотрудника в месяц | C110: тыс. руб./месяц | D110: 300 | E110: =D110 -> 300 | F110: =E110 -> 300 | G110: =F110 -> 300 | H110: =G110 -> 300 | I110: =E110*1.1 -> 330 | J110: =I110*1.1 -> 363 | K110: =J110*1.1 -> 399.3
B111: Кол-во месяцев | C111: мес. | D111: 0 | E111: =E107 -> 3 | F111: =F107 -> 3 | G111: =G107 -> 3 | H111: =H107 -> 3 | I111: =I107 -> 12 | J111: =J107 -> 12 | K111: =K107 -> 12 | O111: техподдержка уровней L1 и L2 - 2 FTE начиная с 1 месяца внедрения
B112: FTE | C112: чел. | D112: 2 | E112: =D112 -> 2 | F112: =E112 -> 2 | G112: =F112 -> 2 | H112: =G112 -> 2 | I112: =H112 -> 2 | J112: =I112 -> 2 | K112: =J112 -> 2
B114: Затраты на тех. поддержку L3 (VK tech)
B115: З/п 1 сотрудника в месяц | C115: тыс. руб./месяц | D115: 500 | E115: =D115 -> 500 | F115: =E115 -> 500 | G115: =F115 -> 500 | H115: =G115 -> 500 | I115: =H115*1.1 -> 550 | J115: =I115*1.1 -> 605 | K115: =J115*1.1 -> 665.5 | O115: техподдержка L3 VK tech dev platform - расходы на нее должны начаться с началом внедрения
B116: Кол-во месяцев | C116: мес. | D116: 0 | E116: =E111 -> 3 | F116: =F111 -> 3 | G116: =G111 -> 3 | H116: =H111 -> 3 | I116: =I111 -> 12 | J116: =J111 -> 12 | K116: =K111 -> 12
B117: FTE | C117: чел. | D117: =Dev_Platform_Hosted_Git!E36 -> 0 | E117: =SUMPRODUCT(Dev_Platform_Hosted_Git!F36:H36,Dev_Platform_Hosted_Git!F40:H40)/SUM(Dev_Platform_Hosted_Git!F40:H40) -> 0.66666667 | F117: =Dev_Platform_Hosted_Git!K36 -> 4 | G117: =Dev_Platform_Hosted_Git!N36 -> 4 | H117: =Dev_Platform_Hosted_Git!Q36 -> 4 | I117: =H117 -> 4 | J117: =I117 -> 4 | K117: =J117 -> 4
B120: Расчет окупаемости проекта
D122: =DATE(2023,12,1) -> 45261 | E122: =DATE(2024,2,15) -> 45337 | F122: =DATE(2024,5,15) -> 45427 | G122: =DATE(2024,8,15) -> 45519 | H122: =DATE(2024,11,15) -> 45611 | I122: =DATE(2025,6,30) -> 45838 | J122: =DATE(2026,6,30) -> 46203 | K122: =DATE(2027,6,30) -> 46568
B123: Показатель | C123: Ед. изм. | D123: 2023 | E123: 1Q 2024 | F123: 2Q 2024 | G123: 3Q 2024 | H123: 4Q 2024 | I123: 2025 | J123: 2026 | K123: 2027
B124: Экономия затрат (GitFlic) | C124: тыс. руб. | D124: =CHOOSE($M$124,D13,D58) -> 0 | E124: =CHOOSE($M$124,E13,E58) -> 13873.188 | F124: =CHOOSE($M$124,F13,F58) -> 26832.468 | G124: =CHOOSE($M$124,G13,G58) -> 26832.468 | H124: =CHOOSE($M$124,H13,H58) -> 40529.748 | I124: =CHOOSE($M$124,I13,I58) -> 224789.26 | J124: =CHOOSE($M$124,J13,J58) -> 215708.8 | K124: =CHOOSE($M$124,K13,K58) -> 217076.19 | M124: 1
B125: Расходы на создание и поддержание собств. платформы | C125: тыс. руб. | D125: =-D102 -> -7000 | E125: =-E102 -> -32124.193 | F125: =-F102 -> -37124.193 | G125: =-G102 -> -37124.193 | H125: =-H102 -> -37124.193 | I125: =-I102 -> -51936.67 | J125: =-J102 -> -42302.337 | K125: =-K102 -> -46532.571
...

Sheet Inputs
B2: Инвестиционная оценка разработки собственного аналога Gitlab Premium | C2: Покупка лицензии | D2: Собственная разработка | G2: Оба варианта находятся в доработке.
C3: GitFlic | D3: VK Tech Dev Platform | G3: Gitflick закроет наши потребности а Q4 2024 при выполнении заявленных планов доработки.
B4: Затраты VK на лицензии на 1 пользователя в месяц, тыс. руб. | C4: 3.6 | G4: VK Tech чтобы закрыть наши планы в Q4 2024 необходимо инвестировать в ФОТ.
B5: Затраты VK на лицензии на 5133 пользователей в год, тыс. руб. | C5: =C4*5133*12 -> 221745.6 | E5: 5133
B6: Инвестиции VK на разработку, тыс. руб. | C6: 0
B7: Затраты VK на внедрение, тыс. руб | C7: 33000
B8: Стоимость для VK владения решением в год, тыс. руб. | C8: 0
B12: Доходы VK от продажи лицензии на 1 пользователя в месяц, тыс. руб | C12: 0 | D12: Ожидаем информацию, но отдельно от Dev Platform не продается
B13: Прогноз продаж лицензий в год, тыс. руб (справочно) | C13: 0 | D13: Ожидаем информацию, но отдельно от Dev Platform не продается

Sheet Dev_Platform_Hosted_Git
B1: Releases | H1: Release 1 | J1: Release 2 | K1: Release 3 | L1: Release 4 | M1: Release 5 | O1: Release 6 | Q1: Release 7
H2: - Remote repository pull mirroring - Code owners - Merge request approval rules - Code Quality Reports - Merge rules - Multiple approvers in code review - Merge request approval settings - Protected Environments - Merged results pipelines - Запрет мержа без получения апрува всех ревьюверов - Web IDE | J2: - Push Rules | K2: - Restrict push and merge access to certain users | L2: - Jira Development Panel Integration | M2: - Merge Trains | O2: - Code Coverage - Verified Committer | Q2: - Advanced Search - Contributor Analytics
B3: Готовность фичей для БЮ | H3: - Департамент консолидированных цифровых решений для бизнеса | J3: - Mail.ru - Департамент рекламных технологий | K3: - Блок ИБ - Технический департамент | L3: - БЮ по медиастратегии и развитию сервисов - Юла - Департамент аналитики и больших данных - БЮ Карты - БЮ Технологий ИИ | M3: - VK tech | O3: - RuStore | Q3: - VK Play - ВКонтакте
D4: 2023 | E4: 2023 | F4: 2024 | G4: 2024 | H4: 2024 | I4: 2024 | J4: 2024 | K4: 2024 | L4: 2024 | M4: 2024 | N4: 2024 | O4: 2024 | P4: 2024 | Q4: 2024
D5: Nov | E5: Dec | F5: Jan | G5: Feb | H5: Mar | I5: Apr | J5: May | K5: Jun | L5: Jul | M5: Aug | N5: Sep | O5: Oct | P5: Nov | Q5: Dec | T5: Jan-Dec 2024
B6: Delivery Manager | F6: 1 | G6: 1 | H6: 1 | I6: 1 | J6: 1 | K6: 1 | L6: 1 | M6: 1 | N6: 1 | O6: 1 | P6: 1 | Q6: 1
B7: Architect | D7: 1 | E7: 1 | F7: 1 | G7: 1 | H7: 1 | I7: 1 | J7: 1 | K7: 1 | L7: 1 | M7: 1 | N7: 1 | O7: 1 | P7: 1 | Q7: 1
B8: Frontend Engineer | E8: 2 | F8: 2 | G8: 2 | H8: 2 | I8: 2 | J8: 2 | K8: 2 | L8: 2 | M8: 2 | N8: 2 | O8: 2 | P8: 2 | Q8: 2
B9: Backend Enginer | E9: 3 | F9: 3 | G9: 3 | H9: 3 | I9: 3 | J9: 3 | K9: 3 | L9: 3 | M9: 3 | N9: 3 | O9: 3 | P9: 3 | Q9: 3
B10: QA Engineer | E10: 3 | F10: 3 | G10: 3 | H10: 3 | I10: 3 | J10: 3 | K10: 3 | L10: 3 | M10: 3 | N10: 3 | O10: 3 | P10: 3 | Q10: 3
B11: System Analyst | D11: 1 | E11: 1 | F11: 1 | G11: 1 | H11: 1 | I11: 1 | J11: 1 | K11: 1 | L11: 1 | M11: 1 | N11: 1 | O11: 1 | P11: 1 | Q11: 1
B12: DevOPS Engineer | G12: 1 | H12: 1 | I12: 1 | J12: 1 | K12: 1 | L12: 1 | M12: 1 | N12: 1 | O12: 1 | P12: 1 | Q12: 1
B13: Desiger | D13: 1 | E13: 1 | F13: 1 | G13: 1 | H13: 1 | I13: 1 | J13: 1 | K13: 1 | L13: 1 | M13: 1 | N13: 1 | O13: 1 | P13: 1 | Q13: 1
B14: Tech Writer | F14: 1 | G14: 1 | H14: 1 | I14: 1
B15: FTE | D15: =SUM(D6:D14) -> 3 | E15: =SUM(E6:E14) -> 11 | F15: =SUM(F6:F14) -> 13 | G15: =SUM(G6:G14) -> 14 | H15: =SUM(H6:H14) -> 14 | I15: =SUM(I6:I14) -> 14 | J15: =SUM(J6:J14) -> 13 | K15: =SUM(K6:K14) -> 13 | ... Q15: =SUM(Q6:Q14) -> 13
B16: FTE cost, 000 | D16: =-SAP!B11/10^3 -> -445.11306 | E16: =D16 -> -445.11306 | F16: =E16*1.05 -> -467.36872 | G16: =F16 -> -467.36872 | H16: =G16 -> -467.36872 | I16: =H16 -> -467.36872 | J16: =I16 -> -467.36872 | K16: =J16 -> -467.36872 | L16: =K16 -> -467.36872 | M16: =L16 -> -467.36872 | N16: =M16 -> -467.36872 | ... Q16: =P16 -> -467.36872
B17: ФОТ (SAP) | D17: =D15*D16 -> -1335.3392 | E17: =E15*E16 -> -4896.2437 | F17: =F15*F16 -> -6075.7933 | G17: =G15*G16 -> -6543.1621 | H17: =H15*H16 -> -6543.1621 | I17: =I15*I16 -> -6543.1621 | J17: =J15*J16 -> -6075.7933 | K17: =K15*K16 -> -6075.7933 | ... Q17: =Q15*Q16 -> -6075.7933
A18: FTE cost, 000 | B18: 500
A19: ФОТ | C19: =R19 -> 86500 | D19: =D15*B18 -> 1500 | E19: =E15*B18 -> 5500 | F19: =F15*B18 -> 6500 | G19: =G15*B18 -> 7000 | H19: =H15*B18 -> 7000 | I19: =I15*B18 -> 7000 | J19: =J15*B18 -> 6500 | K19: =K15*B18 -> 6500 | L19: =L15*B18 -> 6500 | M19: =M15*B18 -> 6500 | N19: =N15*B18 -> 6500 | O19: =O15*B18 -> 6500 | P19: =P15*B18 -> 6500 | Q19: =Q15*B18 -> 6500 | R19: =SUM(D19:Q19) -> 86500
B21: Внедрение | D21: Nov | E21: Dec | F21: Jan | G21: Feb | H21: Mar | I21: Apr | J21: May | K21: Jun | L21: Jul | M21: Aug | N21: Sep | O21: Oct | P21: Nov | Q21: Dec | T21: Jan-Dec 2024
B22: Project Manager | F22: 1 | G22: 1 | H22: 1 | I22: 1 | J22: 1 | K22: 1 | L22: 1 | M22: 1 | N22: 1 | O22: 1 | P22: 1 | Q22: 1
B23: Dev OPS | H23: 2 | I23: 2 | J23: 2 | K23: 4 | L23: 4 | M23: 4 | N23: 4 | O23: 4 | P23: 4 | Q23: 4
B25: FTE | D25: =SUM(D22:D24) -> 0 | E25: =SUM(E22:E24) -> 0 | F25: =SUM(F22:F24) -> 1 | G25: =SUM(G22:G24) -> 1 | H25: =SUM(H22:H24) -> 3 | I25: =SUM(I22:I24) -> 3 | J25: =SUM(J22:J24) -> 3 | K25: =SUM(K22:K24) -> 5 | ... Q25: =SUM(Q22:Q24) -> 5
A26: FTE cost, 000 | B26: 500
A27: ФОТ | B27: 2024 год | C27: =R27 -> 23000 | D27: =B26*D25 -> 0 | E27: =$B26*E25 -> 0 | F27: =$B26*F25 -> 500 | G27: =$B26*G25 -> 500 | H27: =$B26*H25 -> 1500 | I27: =$B26*I25 -> 1500 | J27: =$B26*J25 -> 1500 | K27: =$B26*K25 -> 2500 | L27: =$B26*L25 -> 2500 | ... Q27: =$B26*Q25 -> 2500 | R27: =SUM(D27:Q27) -> 23000 | T27: =R27/2 -> 11500
B28: 2025 год | C28: =T27 -> 11500
B29: FTE cost, 000 | D29: =-SAP!B12/10^3 -> 445.11306 | E29: =D29 -> 445.11306 | F29: =E29*1.05 -> 467.36872 | G29: =F29 -> 467.36872 | H29: =G29 -> 467.36872 | I29: =H29 -> 467.36872 | J29: =I29 -> 467.36872 | K29: =J29 -> 467.36872 | L29: =K29 -> 467.36872 | M29: =L29 -> 467.36872 | N29: =M29 -> 467.36872 | ... Q29: =P29 -> 467.36872
B30: ФОТ (SAP) | D30: =D25*D29 -> 0 | E30: =E25*E29 -> 0 | F30: =F25*F29 -> 467.36872 | G30: =G25*G29 -> 467.36872 | H30: =H25*H29 -> 1402.1062 | I30: =I25*I29 -> 1402.1062 | J30: =J25*J29 -> 1402.1062 | K30: =K25*K29 -> 2336.8436 | ... Q30: =Q25*Q29 -> 2336.8436
B33: Поддержка/багфикс | D33: 0 | E33: 0 | F33: 0 | G33: 0 | H33: 0 | I33: 1 | J33: 1 | K33: 1 | L33: 1 | M33: 1 | N33: 1 | O33: 1 | P33: 1 | Q33: 1
B34: Багфикс | D34: 0 | E34: 0 | F34: 0 | G34: 0 | H34: 0 | I34: 1 | J34: 1 | K34: 1 | L34: 1 | M34: 1 | N34: 1 | O34: 1 | P34: 1 | Q34: 1
B35: Support Dev | H35: 2 | I35: 2 | J35: 2 | K35: 2 | L35: 2 | M35: 2 | N35: 2 | O35: 2 | P35: 2 | Q35: 2
B36: FTE | D36: =SUM(D33:D35) -> 0 | E36: =SUM(E33:E35) -> 0 | F36: =SUM(F33:F35) -> 0 | G36: =SUM(G33:G35) -> 0 | H36: =SUM(H33:H35) -> 2 | I36: =SUM(I33:I35) -> 4 | J36: =SUM(J33:J35) -> 4 | K36: =SUM(K33:K35) -> 4 | ... Q36: =SUM(Q33:Q35) -> 4
A37: FTE cost, 000 | B37: 500
A38: ФОТ | B38: 2024 год | C38: =SUM(D38:Q38) -> 19000 | D38: =$B37*D36 -> 0 | E38: =$B37*E36 -> 0 | F38: =$B37*F36 -> 0 | G38: =$B37*G36 -> 0 | H38: =$B37*H36 -> 1000 | I38: =$B37*I36 -> 2000 | J38: =$B37*J36 -> 2000 | K38: =$B37*K36 -> 2000 | ... Q38: =$B37*Q36 -> 2000
B39: 2025 год | C39: =C38 -> 19000
B40: FTE cost, 000 | D40: =-SAP!B12/10^3 -> 445.11306 | E40: =D40 -> 445.11306 | F40: =E40*1.05 -> 467.36872 | G40: =F40 -> 467.36872 | H40: =G40 -> 467.36872 | I40: =H40 -> 467.36872 | J40: =I40 -> 467.36872 | K40: =J40 -> 467.36872 | L40: =K40 -> 467.36872 | M40: =L40 -> 467.36872 | N40: =M40 -> 467.36872 | ... Q40: =P40 -> 467.36872
B41: ФОТ (SAP) | D41: =D36*D40 -> 0 | E41: =E36*E40 -> 0 | F41: =F36*F40 -> 0 | G41: =G36*G40 -> 0 | H41: =H36*H40 -> 934.73744 | I41: =I36*I40 -> 1869.4749 | J41: =J36*J40 -> 1869.4749 | K41: =K36*K40 -> 1869.4749 | ... Q41: =Q36*Q40 -> 1869.4749

Sheet Лицензии GitFlic
B1: Конец Q4 2023 (169 лицензий) | C1: Конец Q1 2024 (1317 лицензий) | D1: Конец Q2 2024 (0 лицензий) | E1: Конец Q3 2024 (~1392 лицензии) | F1: Конец Q4 2024 ~1900 лицензий | G1: 2025 и далее
B2: Multiple approvers in code review | C2: Verified Committer | D2: Container Scanning* | E2: Code Quality Reports - Технический департамент (409 лицензий) | F2: Contributor Analytics - Вконтакте (1850 лицензий)
B3: Push rules | C3: Audit Events | D3: Protected Environments | E3: Merge Trains (RuStore 218 лицензий, VK Tech 765 лицензий) | F3: Advanced Search - ВКонтакте (1850 лицензий)
B4: Merge request approval settings | C4: Merged results pipelines | D4: Secret Detection | F4: Time Tracking* - VK Play (> 50 чел)
B5: Remote repository pull mirroring | C5: Jira Development Panel Integration (по запросу) | D5: Code Coverage
B6: Code owners | C6: Merge rules (по запросу) | D6: Test Coverage Visualization
B7: Merge request approval rules | D7: Vulnerability Management
B8: Restrict push and merge access to certain users
B9: Advanced LDAP/SAML support, Group Sync
B10: Запрет мержа без апрува всех ревьюверов
A12: Кол-во лицензий | B12: 169 | C12: 1317 | D12: 0 | E12: 1392 | F12: 1900 | G12: =H12-SUM(B12:F12) -> 355 | H12: =Inputs!E5 -> 5133
A13: Кол-во месяцев пользования | B13: 2 | C13: 10 | D13: 9 | E13: 4 | F13: 2
A19: Средневзвешенное кол-во месяцев | C19: =SUMPRODUCT(B12:F12,B13:F13)/SUM(B12:F12) -> 4.7877773
B22: =B12*B13*Calc!D16*(1-Calc!D20) -> 973.44 | C22: =C12*C13*Calc!E16*(1-Calc!E20) -> 37929.6 | D22: =D12*D13*Calc!I16*(1-Calc!I20) -> 0 | E22: =E12*E13*Calc!J16*(1-Calc!J20) -> 16035.84 | F22: =F12*F13*Calc!K16*(1-Calc!K20) -> 10944

Sheet SAP
A1: Budget 2024 v.2 | B1: Amount | C1: MRCS VK Cloud Solutions | F1: Budget 2024 v.2 | G1: MRCS VK Cloud Solutions | H1: All Turnovers | I1: Before Allocation
B2: Year | G2: Year
A3: FOT PL | B3: -1.7720662e+09 | F3: Other_revenue | G3: 108600000
A4: FOT CAPEX | B4: -7.0543315e+08 | F4: B2B Services | G4: 520000000
A5: Total FOT | B5: -2.4774993e+09 | F5: License fee revenue | G5: 7.8072503e+08
A6: Outsource PL | B6: -4.65e+08 | F6: B2B Subscription Revenue | G6: 2.653796e+09
A7: Total Outsource | B7: -4.65e+08 | F7: B2B Subscription Revenue - Cons Sales | G7: 539444426
A8: Total FOT+Outsource | B8: -2.9424993e+09 | F8: Other revenue | G8: 4.6025655e+09
A9: Headcount OPEX | B9: 463.83333 | F9: Revenues | G9: 4.6025655e+09
A10: Headcount ALL | B10: 463.83333 | F10: Salary + Vacation reserve | G10: -1.3748818e+09
A11: FOT monthly per employee | B11: 445113.06 | F11: Social tax | G11: -54635172
B12: =B5/B9/12 -> -445113.06 | F12: Operating bonus | G12: -1.2660206e+08
F13: Annual bonus | G13: -2.1594715e+08
F14: Other personnel expenses | G14: -999999.96
F15: Medical insurance | G15: -38642841
F16: Meals | G16: -37106667
F17: Reimbursements | G17: -5537659.5
F18: Personnel expenses | G18: -1.8543533e+09
F19: Outsource | G19: -4.65e+08
F20: Other partners fees | G20: -90000000
F21: Partners fees & Royalties | G21: -90000000
F22: SMS notification | G22: -327600
F23: Advertising - online | G23: -94174400
F24: Marketing partnership and sponsorship | G24: -5500000
... F56: Net Profit/Loss attributable to equity holders of the parent | G56: 9.8139613e+08
F58: Накладные и прочие расходы | G58: =SUM(G14:G17,G38,G43) -> -95620573
F59: Расходы на 1 штатного сотрудника в год | G59: =G58/B9 -> -206152.87
