Workbook

Sheet Объем рынка
A1: Легенда: черным - вводные данные; синим - расчет
A2: Рынок | B2: ед. изм. | C2: 2022 | D2: =C2+1 -> 2023 | E2: =D2+1 -> 2024 | F2: =E2+1 -> 2025 | G2: =F2+1 -> 2026 | H2: =G2+1 -> 2027 | J2: CAGR 2023-2027 гг., % | L2: Источник | M2: Ссылка
A3: Экспертные оценки
A4: ASOC | B4: млрд руб. | D4: 4.2 | E4: =D4*(1+$J4) -> 5.04 | F4: =E4*(1+$J4) -> 6.048 | G4: =F4*(1+$J4) -> 7.2576 | H4: =G4*(1+$J4) -> 8.70912 | J4: 0.2 | L4: Наше исследование MTS RED | M4: https://docs.google.com/document/d/1Nv8za5sTC_KYzoQ8pctjLsnvbe2vNXB3jib50V1hk5Y/edit?usp=sharing https://www.tadviser.ru/index.php/%D0%9F%D1%80%D0%BE%D0%B4%D1%83%D0%BA%D1%82:%D0%9C%D0%A2%D0%A1_RED_ASOC_(Application_Security_Orchestration_and_Correlation)
A6: Оценки ЦСР
J7: *Для данных ЦРС CAGR согласно росту рынка ИБ в целом

Sheet Шаблон инициатив для ИБ
A1: Наименование показателя | F1: ед. изм. | H1: 2022 | I1: =H1+1 -> 2023 | J1: =I1+1 -> 2024 | K1: =J1+1 -> 2025 | L1: =K1+1 -> 2026 | M1: =L1+1 -> 2027 | O1: CAGR 2024-27 | Q1: Источник | R1: Ссылка
A2: 1. Рынок
A3: Объем рынка X | F3: млн руб. | I3: ='Объем рынка'!D4*1000 -> 4200 | J3: ='Объем рынка'!E4*1000 -> 5040 | K3: ='Объем рынка'!F4*1000 -> 6048 | L3: ='Объем рынка'!G4*1000 -> 7257.6 | M3: ='Объем рынка'!H4*1000 -> 8709.12 | O3: ='Объем рынка'!J4 -> 0.2
A5: Выручка и доля рынка ключевых игроков | AJ5: product | AK5: 1
B6: SwordFish Security | F6: млн руб. | I6: 615 | J6: =I6*(1+$O6) -> 799.5 | K6: =J6*(1+$O6) -> 1039.35 | L6: =K6*(1+$O6) -> 1351.155 | M6: =L6*(1+$O6) -> 1756.5015 | O6: 0.3 | AJ6: analyst | AK6: 1
C7: Доля рынка | F7: % | I7: =I6/I3 -> 0.14642857 | J7: =J6/J3 -> 0.15863095 | K7: =K6/K3 -> 0.1718502 | L7: =L6/L3 -> 0.18617105 | M7: =M6/M3 -> 0.2016853 | AJ7: teamlead | AK7: 1
B8: Игрок 2 | F8: млн руб. | I8: XX | AJ8: arch | AK8: 1
C9: Доля рынка | F9: % | I9: X% | AJ9: Fronend | AK9: 1
B10: Игрок 3 | F10: млн руб. | I10: XX | AJ10: Backend | AK10: 3
C11: Доля рынка | F11: % | I11: X% | AJ11: Presale | AK11: 1
B12: ... | AK12: =SUM(AK5:AK11) -> 9 | AL12: 550 | AM12: =AL12*12*AK12 -> 59400
A14: 2. P&L инициативы
A15: Выручка VK Tech | F15: млн руб. | J15: 60 | K15: =J15*(1+$O15) -> 84 | L15: =K15*(1+$O15) -> 117.6 | M15: =L15*(1+$O15) -> 164.64 | O15: 0.4
B16: Доля рынка VK Tech | F16: % | J16: =J15/J3 -> 0.011904762 | K16: =K15/K3 -> 0.013888889 | L16: =L15/L3 -> 0.016203704 | M16: =M15/M3 -> 0.018904321
A17: OPEX | F17: млн руб. | J17: =J20 -> 59.4 | K17: =K20 -> 59.4 | L17: =L20 -> 59.4 | M17: =M20 -> 59.4
B18: ФОТ | F18: млн руб.
C19: Численность | F19: ед. | J19: =AK12 -> 9 | K19: =J19 -> 9 | L19: =K19 -> 9 | M19: =L19 -> 9
C20: Ср. расходы на персонал | F20: млн руб. / год | J20: =AM12/1000 -> 59.4 | K20: =J20 -> 59.4 | L20: =K20 -> 59.4 | M20: =L20 -> 59.4
B21: ...
B22: ...
A23: EBITDA | F23: млн руб. | J23: =J15-J20 -> 0.6 | K23: =K15-K20 -> 24.6 | L23: =L15-L20 -> 58.2 | M23: =M15-M20 -> 105.24
A24: CAPEX | F24: млн руб.
B25: ...
B26: ...
A27: FCF проекта | F27: млн руб.
A29: 3. Основные этапы и сроки реализации
A30: № | C30: Описание этапа | L30: Сроки реализации (кв., год) | O30: Ответственный
A31: 1 | C31: Реализация варианта поставки on-prem | L31: 6 месяцев
A32: 2
A33: 3
A34: ...
A37: 4. Ключевые риски реализации
A38: № | C38: Описание риска | K38: Меры по митигации риска
A39: 1
A40: 2
A41: 3
A42: ...
